realtimex_deeptutor/__init__.py
realtimex_deeptutor-0.5.0.post6.dist-info/licenses/LICENSE
scripts/__init__.py
scripts/audit_prompts.py
scripts/check_install.py
scripts/generate_roster.py
scripts/install_all.py
scripts/migrate_kb.py
scripts/start.py
scripts/start_web.py
scripts/sync_prompts_from_en.py
src/__init__.py
src/agents/__init__.py
src/agents/base_agent.py
src/agents/chat/__init__.py
src/agents/chat/chat_agent.py
src/agents/chat/session_manager.py
src/agents/chat/prompts/en/chat_agent.yaml
src/agents/chat/prompts/zh/chat_agent.yaml
src/agents/co_writer/__init__.py
src/agents/co_writer/edit_agent.py
src/agents/co_writer/narrator_agent.py
src/agents/co_writer/prompts/en/edit_agent.yaml
src/agents/co_writer/prompts/en/narrator_agent.yaml
src/agents/co_writer/prompts/zh/edit_agent.yaml
src/agents/co_writer/prompts/zh/narrator_agent.yaml
src/agents/guide/__init__.py
src/agents/guide/guide_manager.py
src/agents/guide/agents/__init__.py
src/agents/guide/agents/chat_agent.py
src/agents/guide/agents/interactive_agent.py
src/agents/guide/agents/locate_agent.py
src/agents/guide/agents/summary_agent.py
src/agents/guide/prompts/en/chat_agent.yaml
src/agents/guide/prompts/en/interactive_agent.yaml
src/agents/guide/prompts/en/locate_agent.yaml
src/agents/guide/prompts/en/summary_agent.yaml
src/agents/guide/prompts/zh/chat_agent.yaml
src/agents/guide/prompts/zh/interactive_agent.yaml
src/agents/guide/prompts/zh/locate_agent.yaml
src/agents/guide/prompts/zh/summary_agent.yaml
src/agents/ideagen/__init__.py
src/agents/ideagen/idea_generation_workflow.py
src/agents/ideagen/material_organizer_agent.py
src/agents/ideagen/prompts/en/idea_generation.yaml
src/agents/ideagen/prompts/en/material_organizer.yaml
src/agents/ideagen/prompts/zh/idea_generation.yaml
src/agents/ideagen/prompts/zh/material_organizer.yaml
src/agents/question/__init__.py
src/agents/question/coordinator.py
src/agents/question/example.py
src/agents/question/agents/__init__.py
src/agents/question/agents/generate_agent.py
src/agents/question/agents/relevance_analyzer.py
realtimex_deeptutor-0.5.0.post6.dist-info/METADATA
realtimex_deeptutor-0.5.0.post6.dist-info/WHEEL
realtimex_deeptutor-0.5.0.post6.dist-info/entry_points.txt
realtimex_deeptutor-0.5.0.post6.dist-info/top_level.txt
realtimex_deeptutor-0.5.0.post6.dist-info/RECORD
