Metadata-Version: 2.4
Name: realtimex-deeptutor
Version: 0.5.0.post6
Summary: RealTimeX DeepTutor - Intelligent learning companion with multi-agent collaboration and LightRAG
License: Apache-2.0
Requires-Python: >=3.10
License-File: LICENSE
Requires-Dist: python-dotenv>=1.0.0
Requires-Dist: PyYAML>=6.0
Requires-Dist: tiktoken>=0.5.0
Requires-Dist: jinja2>=3.1.0
Requires-Dist: requests>=2.32.2
Requires-Dist: openai>=1.30.0
Requires-Dist: aiohttp>=3.9.4
Requires-Dist: httpx>=0.27.0
Requires-Dist: nest_asyncio>=1.5.8
Requires-Dist: tenacity>=8.0.0
Requires-Dist: fastapi>=0.100.0
Requires-Dist: uvicorn[standard]>=0.24.0
Requires-Dist: websockets>=12.0
Requires-Dist: python-multipart>=0.0.6
Requires-Dist: pydantic>=2.0.0
Requires-Dist: pydantic-settings>=2.12.0
Requires-Dist: lightrag-hku>=1.0.0
Requires-Dist: PyMuPDF>=1.26.0
Requires-Dist: numpy<2.0.0,>=1.24.0
Requires-Dist: arxiv>=2.0.0
Requires-Dist: realtimex-sdk>=1.1.2
Provides-Extra: anthropic
Requires-Dist: anthropic>=0.30.0; extra == "anthropic"
Provides-Extra: dashscope
Requires-Dist: dashscope>=1.14.0; extra == "dashscope"
Provides-Extra: search
Requires-Dist: perplexityai>=0.1.0; extra == "search"
Provides-Extra: raganything
Requires-Dist: raganything>=0.1.0; extra == "raganything"
Provides-Extra: llamaindex
Requires-Dist: llama-index>=0.14.12; extra == "llamaindex"
Provides-Extra: academic
Requires-Dist: arxiv>=2.0.0; extra == "academic"
Provides-Extra: all
Requires-Dist: anthropic>=0.30.0; extra == "all"
Requires-Dist: dashscope>=1.14.0; extra == "all"
Requires-Dist: perplexityai>=0.1.0; extra == "all"
Requires-Dist: raganything>=0.1.0; extra == "all"
Requires-Dist: llama-index>=0.14.12; extra == "all"
Requires-Dist: arxiv>=2.0.0; extra == "all"
Provides-Extra: dev
Requires-Dist: pytest>=7.0.0; extra == "dev"
Requires-Dist: pre-commit>=3.0.0; extra == "dev"
Requires-Dist: bandit>=1.8.0; extra == "dev"
Dynamic: license-file
